{
   "name": "DHIS2",
   "clearOwnership": {
      "isOwnershipExplicit": "No"
   },
   "platformIndependence": {
      "mandatoryDepsCreateMoreRestrictions": "No"
   },
   "documentation": {
      "isDocumentationAvailable": "No"
   },
   "NonPII": {
      "collectsNonPII": "No"
   },
   "privacy": {
      "isPrivacyCompliant": "No"
   },
   "standards": {
      "supportStandards": "No",
      "implementBestPractices": "No"
   },
   "doNoHarm": "",
   "locations": {
      "developmentCountries": [
         "Djibouti"
      ],
      "deploymentCountries": [
         "Botswana"
      ]
   }
}
